harper/__init__.py
harper/audio/__init__.py
harper/audio/extension.py
harper/audio/filters.py
harper/audio/sampling.py
harper/audio/signal.py
harper/audio/smoothers.py
harper/audio/spectogram.py
harper/audio/transforms.py
harper/audio/windows.py
harper/bops.py
harper/exceptions.py
harper/io/__init__.py
harper/io/wavfile.py
harper/media.py
harper/misc.py
harper/music/__init__.py
harper/music/chords.py
harper/music/notes.py
harper/music/scales.py
harper/samples.py
harper/synthesis.py
harper-0.4.5.dist-info/LICENSE.txt
harper-0.4.5.dist-info/WHEEL
harper-0.4.5.dist-info/METADATA
harper-0.4.5.dist-info/RECORD
